LICENSE.txt
README.md
configure.py
pytronix.py
setup.py
trigger-print.py
pytronix.egg-info/PKG-INFO
pytronix.egg-info/SOURCES.txt
pytronix.egg-info/dependency_links.txt
pytronix.egg-info/requires.txt
pytronix.egg-info/top_level.txt