Metadata-Version: 1.0
Name: pytronix
Version: 0.81
Summary: A python project to easily and rapidly download data from TekTronix DSOs
Home-page: https://bitbucket.org/martijnj/pytronix
Author: Martijn Jasperse
Author-email: m.jasperse@gmail.com
License: BSD
Keywords: tektronix DSO CRO scope HDF5
Platform: UNKNOWN
